picklescan/__init__.py
picklescan/__main__.py
picklescan/cli.py
picklescan/relaxed_zipfile.py
picklescan/scanner.py
picklescan/torch.py
picklescan-0.0.35.dist-info/licenses/LICENSE
picklescan-0.0.35.dist-info/licenses/NOTICE.txt
picklescan-0.0.35.dist-info/METADATA
picklescan-0.0.35.dist-info/WHEEL
picklescan-0.0.35.dist-info/entry_points.txt
picklescan-0.0.35.dist-info/top_level.txt
picklescan-0.0.35.dist-info/RECORD
