Metadata-Version: 2.4
Name: picklescan
Version: 0.0.35
Summary: Security scanner detecting Python Pickle files performing suspicious actions
Home-page: https://github.com/mmaitre314/picklescan
Author: Matthieu Maitre
Author-email: mmaitre314@users.noreply.github.com
Project-URL: Bug Tracker, https://github.com/mmaitre314/picklescan/issues
Classifier: Programming Language :: Python :: 3
Classifier: License :: OSI Approved :: MIT License
Classifier: Operating System :: OS Independent
Requires-Python: >=3.9
License-File: LICENSE
License-File: NOTICE.txt
Provides-Extra: 7z
Requires-Dist: py7zr; extra == "7z"
Dynamic: license-file
